README.md
setup.py
command_manager/__init__.py
command_manager/exceptions.py
command_manager/manager.py
command_manager/utils.py
command_manager.egg-info/PKG-INFO
command_manager.egg-info/SOURCES.txt
command_manager.egg-info/dependency_links.txt
command_manager.egg-info/top_level.txt
command_manager/commands/__init__.py
command_manager/commands/base_command.py