Metadata-Version: 1.1
Name: command-manager
Version: 1.2.0
Summary: Entry point for Python scripts
Home-page: https://github.com/falgore88/command_manager/
Author: Evgeniy Titov
Author-email: falgore88@gmail.com
License: BSD
Download-URL: https://github.com/falgore88/command_manager/tarball/v1.2.0
Platform: UNKNOWN
Classifier: Development Status :: 5 - Production/Stable
Classifier: Environment :: Web Environment
Classifier: Environment :: X11 Applications
Classifier: Environment :: Console
Classifier: Framework :: Django
Classifier: Operating System :: OS Independent
Classifier: Programming Language :: Python
Classifier: Programming Language :: Python :: 2
Classifier: Programming Language :: Python :: 2.7
Classifier: Programming Language :: Python :: 3
Classifier: Programming Language :: Python :: 3.5
Classifier: License :: OSI Approved :: BSD License
Classifier: Topic :: Software Development :: Libraries :: Python Modules
